README.rst
ez_setup.py
setup.py
mutils/__init__.py
mutils/version.py
mutils.egg-info/PKG-INFO
mutils.egg-info/SOURCES.txt
mutils.egg-info/dependency_links.txt
mutils.egg-info/requires.txt
mutils.egg-info/top_level.txt
mutils/html/__init__.py
mutils/html/parser.py
mutils/image/__init__.py
mutils/image/imageinfo.py
mutils/misc/__init__.py
mutils/misc/colors.py
mutils/misc/colortrans.py
mutils/misc/docstring.py
mutils/system/__init__.py
mutils/system/common.py
mutils/system/scheduler.py
mutils/system/sys_command.py
mutils/system/terminalsize.py
mutils/test/__init__.py
mutils/test/html/__init__.py
mutils/test/html/testparser.py
mutils/test/misc/__init__.py
mutils/test/misc/test_docstring.py
mutils/test/web/__init__.py
mutils/test/web/testurls.py
mutils/web/__init__.py
mutils/web/cdns.py
mutils/web/tlds.py
mutils/web/update_cdns.py
mutils/web/update_tlds.py
mutils/web/urls.py